{
  "dataset_root": "dataset",
  "global_loader": "cv2.IMREAD_GRAYSCALE",
  "global_channels": 1,
  "splits": {
    "train": {
      "matched_records": 5491,
      "used_records": 5491,
      "csv_columns": [
        "ID",
        "Male",
        "Boneage",
        "Chronological"
      ],
      "sex_field": "Male",
      "chronological_field": "Chronological",
      "boneage_field": "Boneage",
      "has_boneage_targets": true,
      "missing_target_count_in_used_records": 0,
      "sex_distribution": {
        "0": 3119,
        "1": 2372
      },
      "chronological_range": {
        "min": 10.0,
        "max": 242.0
      },
      "boneage_range": {
        "min": 12.0,
        "max": 228.0
      },
      "image_extensions": [
        ".png"
      ],
      "sample_id_preview": [
        "00001",
        "00002",
        "00003",
        "00004",
        "00005"
      ],
      "image_dir": "dataset/RHPE_train",
      "csv_path": "dataset/RHPE_Annotations/RHPE_Boneage_train.csv",
      "roi_json_path": "dataset/RHPE_Annotations/RHPE_anatomical_ROIs_train.json",
      "id_width": 5
    },
    "val": {
      "matched_records": 713,
      "used_records": 713,
      "csv_columns": [
        "ID",
        "Male",
        "Boneage",
        "Chronological"
      ],
      "sex_field": "Male",
      "chronological_field": "Chronological",
      "boneage_field": "Boneage",
      "has_boneage_targets": true,
      "missing_target_count_in_used_records": 0,
      "sex_distribution": {
        "0": 407,
        "1": 306
      },
      "chronological_range": {
        "min": 11.0,
        "max": 265.0
      },
      "boneage_range": {
        "min": 12.0,
        "max": 228.0
      },
      "image_extensions": [
        ".png"
      ],
      "sample_id_preview": [
        "05497",
        "05498",
        "05499",
        "05500",
        "05501"
      ],
      "image_dir": "dataset/RHPE_val",
      "csv_path": "dataset/RHPE_Annotations/RHPE_Boneage_val.csv",
      "roi_json_path": "dataset/RHPE_Annotations/RHPE_anatomical_ROIs_val.json",
      "id_width": 5
    },
    "test": {
      "matched_records": 79,
      "used_records": 79,
      "csv_columns": [
        "ID",
        "Male",
        "Chronological"
      ],
      "sex_field": "Male",
      "chronological_field": "Chronological",
      "boneage_field": null,
      "has_boneage_targets": false,
      "missing_target_count_in_used_records": 79,
      "sex_distribution": {
        "0": 41,
        "1": 38
      },
      "chronological_range": {
        "min": 29.0,
        "max": 201.0
      },
      "boneage_range": null,
      "image_extensions": [
        ".png"
      ],
      "sample_id_preview": [
        "06213",
        "06214",
        "06215",
        "06216",
        "06217"
      ],
      "image_dir": "dataset/RHPE_test",
      "csv_path": "dataset/RHPE_Annotations/RHPE_Gender_Chronological_test.csv",
      "roi_json_path": "dataset/RHPE_Annotations/RHPE_anatomical_ROIs_test.json",
      "id_width": 5
    }
  }
}